rjango/__init__.py
rjango/graphql/__init__.py
rjango.graphql-0.1.0.dist-info/METADATA
rjango.graphql-0.1.0.dist-info/WHEEL
rjango.graphql-0.1.0.dist-info/top_level.txt
rjango.graphql-0.1.0.dist-info/RECORD
